setup.py
salt_metrics.egg-info/PKG-INFO
salt_metrics.egg-info/SOURCES.txt
salt_metrics.egg-info/dependency_links.txt
salt_metrics.egg-info/requires.txt
salt_metrics.egg-info/top_level.txt
saltmetrics/__init__.py
saltmetrics/metadata.py
saltmetrics/metrics.py
saltmetrics/utils/__init__.py
saltmetrics/utils/event.py