Metadata-Version: 1.0
Name: salt-metrics
Version: 0.0.3
Summary: Salt Metrics
Home-page: https://github.com/pengyao/salt-metrics
Author: pengyao
Author-email: pengyao@pengyao.org
License: Apache License V2.0
Platform: UNKNOWN
